pymoo-0.6.1.5.dist-info/RECORD
pymoo-0.6.1.5.dist-info/WHEEL
pymoo-0.6.1.5.dist-info/top_level.txt
pymoo-0.6.1.5.dist-info/METADATA
pymoo-0.6.1.5.dist-info/licenses/LICENSE
pymoo/optimize.py
pymoo/config.py
pymoo/version.py
pymoo/__init__.py
pymoo/docs.py
pymoo/visualization/heatmap.py
pymoo/visualization/pcp.py
pymoo/visualization/petal.py
pymoo/visualization/util.py
pymoo/visualization/radar.py
pymoo/visualization/fitness_landscape.py
pymoo/visualization/__init__.py
pymoo/visualization/radviz.py
pymoo/visualization/scatter.py
pymoo/visualization/star_coordinate.py
pymoo/visualization/video/callback_video.py
pymoo/visualization/video/one_var_one_obj.py
pymoo/visualization/video/__init__.py
pymoo/visualization/video/two_var_one_obj.py
pymoo/gradient/automatic.py
pymoo/gradient/__init__.py
pymoo/gradient/grad_jax.py
pymoo/gradient/grad_autograd.py
pymoo/gradient/grad_complex.py
pymoo/gradient/toolbox/__init__.py
pymoo/experimental/__init__.py
pymoo/experimental/algorithms/gde3.py
pymoo/experimental/algorithms/__init__.py
pymoo/core/repair.py
pymoo/core/callback.py
pymoo/core/algorithm.py
pymoo/core/mating.py
pymoo/core/plot.py
pymoo/core/survival.py
pymoo/core/mutation.py
pymoo/core/solution.py
pymoo/core/indicator.py
pymoo/core/population.py
pymoo/core/recorder.py
pymoo/core/termination.py
pymoo/core/operator.py
pymoo/core/__init__.py
pymoo/core/variable.py
pymoo/core/initialization.py
pymoo/core/result.py
pymoo/core/mixed.py
pymoo/core/infill.py
pymoo/core/duplicate.py
pymoo/core/problem.py
pymoo/core/individual.py
pymoo/core/sampling.py
pymoo/core/decomposition.py
pymoo/core/replacement.py
pymoo/core/crossover.py
pymoo/core/parameters.py
pymoo/core/selection.py
pymoo/core/decision_making.py
pymoo/core/evaluator.py
pymoo/core/meta.py
pymoo/constraints/as_penalty.py
pymoo/constraints/as_obj.py
pymoo/constraints/__init__.py
pymoo/constraints/adaptive.py
pymoo/constraints/from_bounds.py
pymoo/constraints/eps.py
pymoo/operators/control.py
pymoo/operators/__init__.py
pymoo/operators/mutation/inversion.py
pymoo/operators/mutation/bitflip.py
