Metadata-Version: 2.4
Name: pymoo
Version: 0.6.1.5
Summary: Multi-Objective Optimization in Python
Author-email: Julian Blank <blankjul@outlook.com>
License-Expression: Apache-2.0
Project-URL: homepage, https://pymoo.org
Keywords: optimization
Classifier: Intended Audience :: Developers
Classifier: Intended Audience :: Science/Research
Classifier: Operating System :: OS Independent
Classifier: Programming Language :: Python
Classifier: Programming Language :: Python :: 3
Classifier: Programming Language :: Python :: 3.9
Classifier: Programming Language :: Python :: 3.10
Classifier: Programming Language :: Python :: 3.11
Classifier: Programming Language :: Python :: 3.12
Classifier: Programming Language :: Python :: 3.13
Classifier: Topic :: Scientific/Engineering
Classifier: Topic :: Scientific/Engineering :: Artificial Intelligence
Classifier: Topic :: Scientific/Engineering :: Mathematics
Requires-Python: >=3.9
License-File: LICENSE
Requires-Dist: numpy>=1.19.3
Requires-Dist: scipy>=1.1
Requires-Dist: matplotlib>=3
Requires-Dist: autograd>=1.4
Requires-Dist: cma>=3.2.2
Requires-Dist: alive-progress
Requires-Dist: dill
Requires-Dist: Deprecated
Dynamic: license-file
